yandex_reviews_parser/__init__.py
yandex_reviews_parser/helpers.py
yandex_reviews_parser/main.py
yandex_reviews_parser/parsers.py
yandex_reviews_parser/storage.py
yandex_reviews_parser/tests/__init__.py
yandex_reviews_parser/tests/test_helpers.py
yandex_reviews_parser/utils.py
yandex_reviews_parser-0.1.4.dist-info/LICENSE
yandex_reviews_parser-0.1.4.dist-info/WHEEL
yandex_reviews_parser-0.1.4.dist-info/METADATA
yandex_reviews_parser-0.1.4.dist-info/RECORD
