Metadata-Version: 2.1
Name: yandex-reviews-parser
Version: 0.1.4
Summary: Python yandex company reviews parser
Home-page: https://github.com/useless-apple/yandex_reviews-parser
License: MIT
Keywords: python,yandex,parser,reviews
Author: Daniil
Author-email: danil16m@mail.ru
Requires-Python: >=3.9,<4.0
Classifier: License :: OSI Approved :: MIT License
Classifier: Programming Language :: Python :: 3
Classifier: Programming Language :: Python :: 3.9
Classifier: Programming Language :: Python :: 3.10
Classifier: Programming Language :: Python :: 3.11
Requires-Dist: undetected-chromedriver (>=3.5.0,<4.0.0)
